dep_common/__init__.py
dep_common/__main__.py
dep_common/args/Args.py
dep_common/args/__init__.py
dep_common/converter/Converter.py
dep_common/converter/__init__.py
dep_common/hash/Hash.py
dep_common/hash/__init__.py
dep_common/msg/MessageFactory.py
dep_common/msg/MessageType.py
dep_common/msg/__init__.py
dep_common/output/Output.py
dep_common/output/__init__.py
dep_common/type/DataState.py
dep_common/type/MessageType.py
dep_common/type/__init__.py
dep_common-1.0.0.dist-info/METADATA
dep_common-1.0.0.dist-info/WHEEL
dep_common-1.0.0.dist-info/entry_points.txt
dep_common-1.0.0.dist-info/top_level.txt
dep_common-1.0.0.dist-info/RECORD
